cellmap_utils/__about__.py
cellmap_utils/__init__.py
cellmap_utils/airtable/__init__.py
cellmap_utils/airtable/pydantic_models.py
cellmap_utils/airtable/filter/__init__.py
cellmap_utils/airtable/filter/filter.py
cellmap_utils/airtable/supabase/__init__.py
cellmap_utils/airtable/supabase/air_to_supabase.py
cellmap_utils/airtable/supabase/pydantic_models.py
cellmap_utils/airtable/upsert/__init__.py
cellmap_utils/airtable/upsert/image.py
cellmap_utils/airtable/upsert/scene.py
cellmap_utils/image/__init__.py
cellmap_utils/image/info.py
cellmap_utils/zarr/__init__.py
cellmap_utils/zarr/metadata.py
cellmap_utils/zarr/node.py
cellmap_utils/zarr/roi.py
cellmap_utils/zarr/store.py
cellmap_utils/zarr/validate.py
cellmap_utils-0.0.33.dist-info/METADATA
cellmap_utils-0.0.33.dist-info/WHEEL
cellmap_utils-0.0.33.dist-info/licenses/LICENSE.txt
cellmap_utils-0.0.33.dist-info/RECORD
